stairs_resource_model/__init__.py
stairs_resource_model/agent_wrapper.py
stairs_resource_model/jobs.py
stairs_resource_model/learning_pipelines/__init__.py
stairs_resource_model/learning_pipelines/new_pipeline.py
stairs_resource_model/learning_pipelines/ttk_pipeline.py
stairs_resource_model/local_mapper/__init__.py
stairs_resource_model/local_mapper/cosine_mapping.py
stairs_resource_model/model/__init__.py
stairs_resource_model/model/networks.py
stairs_resource_model/model/node.py
stairs_resource_model/regressor/__init__.py
stairs_resource_model/regressor/journal.py
stairs_resource_model/res_time_model.py
stairs_resource_model/schema.py
stairsres-0.3.2.dist-info/METADATA
stairsres-0.3.2.dist-info/WHEEL
stairsres-0.3.2.dist-info/RECORD
