Metadata-Version: 2.1
Name: stairsres
Version: 0.3.2
Summary: 
Author: Roman Netrogolov
Author-email: romius2001@gmail.com
Requires-Python: >=3.10,<3.11
Classifier: Programming Language :: Python :: 3
Classifier: Programming Language :: Python :: 3.10
Requires-Dist: bamt_light
Requires-Dist: numpy (>=1.25,<2.0)
